
{
    "TemplateMapping": {
      "CSharp": [
          { "Template": "EntityType", "SubProcessor": "ComplexType", "Type": "Model", "Name": "<Class>", "Matches": "navigable" },
          
          { "Template": "IEntityClient", "SubProcessor": "EntityContainer", "Type": "Client", "Name": "I<Container>Client" },
          
          { "Template": "EntityRequest", "SubProcessor": "ComplexType", "Type": "Request", "Name": "<Class>Request", "Matches": "navigable" },
          { "Template": "IEntityRequest", "SubProcessor": "EntityType", "Type": "Request", "Name": "I<Class>Request" },
          { "Template": "IEntityRequest", "SubProcessor": "ComplexType", "Type": "Request", "Name": "I<Class>Request", "Matches": "navigable" },
          
          { "Template": "EntityRequestBuilder", "SubProcessor": "ComplexType", "Type": "Request", "Name": "<Class>RequestBuilder", "Matches": "navigable" },
          { "Template": "IEntityRequestBuilder", "SubProcessor": "EntityType", "Type": "Request", "Name": "I<Class>RequestBuilder" },
          { "Template": "IEntityRequestBuilder", "SubProcessor": "ComplexType", "Type": "Request", "Name": "I<Class>RequestBuilder", "Matches": "navigable" },
          
          { "Template": "EntityCollectionPage", "SubProcessor": "NavigationCollectionProperty", "Type": "Request", "Name": "<Property>CollectionPage" },
          { "Template": "IEntityCollectionPage", "SubProcessor": "NavigationCollectionProperty", "Type": "Request", "Name": "I<Property>CollectionPage" },
          { "Template": "EntityCollectionRequest", "SubProcessor": "NavigationCollectionProperty", "Type": "Request", "Name": "<Property>CollectionRequest" },
          { "Template": "IEntityCollectionRequest", "SubProcessor": "NavigationCollectionProperty", "Type": "Request", "Name": "I<Property>CollectionRequest" },
          { "Template": "EntityCollectionRequestBuilder", "SubProcessor": "NavigationCollectionProperty", "Type": "Request", "Name": "<Property>CollectionRequestBuilder" },
          { "Template": "IEntityCollectionRequestBuilder", "SubProcessor": "NavigationCollectionProperty", "Type": "Request", "Name": "I<Property>CollectionRequestBuilder" },
          { "Template": "EntityCollectionResponse", "SubProcessor": "NavigationCollectionProperty", "Type": "Request", "Name": "<Property>CollectionResponse" },
          
          { "Template": "StreamRequest", "SubProcessor": "MediaEntityType", "Type": "Request", "Name": "<Class>ContentRequest" },
          { "Template": "IStreamRequest", "SubProcessor": "StreamProperty", "Type": "Request", "Name": "I<Class><Property>Request" },
          { "Template": "IStreamRequest", "SubProcessor": "MediaEntityType", "Type": "Request", "Name": "I<Class>ContentRequest" },
          { "Template": "StreamRequestBuilder", "SubProcessor": "StreamProperty", "Type": "Request", "Name": "<Class><Property>RequestBuilder" },
          { "Template": "StreamRequestBuilder", "SubProcessor": "MediaEntityType", "Type": "Request", "Name": "<Class>ContentRequestBuilder" },
          { "Template": "IStreamRequestBuilder", "SubProcessor": "StreamProperty", "Type": "Request", "Name": "I<Class><Property>RequestBuilder" },
          { "Template": "IStreamRequestBuilder", "SubProcessor": "MediaEntityType", "Type": "Request", "Name": "I<Class>ContentRequestBuilder" },

          { "Template": "MethodAsyncMonitor", "SubProcessor": "Method", "Type": "Request", "Name": "<Class><Method>AsyncMonitor", "Matches": "async" },
          { "Template": "IMethodAsyncMonitor", "SubProcessor": "Method", "Type": "Request", "Name": "I<Class><Method>AsyncMonitor", "Matches": "async" },
          { "Template": "IMethodRequest", "SubProcessor": "Method", "Type": "Request", "Name": "I<Class><Method>Request" },
          { "Template": "IMethodRequestBuilder", "SubProcessor": "Method", "Type": "Request", "Name": "I<Class><Method>RequestBuilder" },
          { "Template": "MethodRequestBody", "SubProcessor": "MethodWithBody", "Type": "Model", "Name": "<Class><Method>RequestBody" },
          { "Template": "MethodCollectionResponse", "SubProcessor": "CollectionMethod", "Type": "Request", "Name": "<Class><Method>CollectionResponse", "Ignore": "ignorableCollection" },
          { "Template": "MethodCollectionResponse", "SubProcessor": "Method", "Type": "Request", "Name": "<Class><Method>CollectionResponse", "Matches": "specialCollection", "Ignore": "ignorableCollection" },
          { "Template": "MethodCollectionPage", "SubProcessor": "CollectionMethod", "Type": "Request", "Name": "<Class><Method>CollectionPage", "Ignore": "ignorableCollection" },
          { "Template": "MethodCollectionPage", "SubProcessor": "Method", "Type": "Request", "Name": "<Class><Method>CollectionPage", "Matches": "specialCollection", "Ignore": "ignorableCollection" },
          { "Template": "IMethodCollectionPage", "SubProcessor": "CollectionMethod", "Type": "Request", "Name": "I<Class><Method>CollectionPage", "Ignore": "ignorableCollection" },
          { "Template": "IMethodCollectionPage", "SubProcessor": "Method", "Type": "Request", "Name": "I<Class><Method>CollectionPage", "Matches": "specialCollection", "Ignore": "ignorableCollection" },
          
          { "Template": "SharedCSharp", "SubProcessor": "Other", "Type": "Shared" }
      ]
    }
}
